pudzu/utils/__init__.py
pudzu/utils/utils.py
pudzu_utils-0.9.3.dist-info/METADATA
pudzu_utils-0.9.3.dist-info/WHEEL
pudzu_utils-0.9.3.dist-info/RECORD
