Metadata-Version: 2.1
Name: pudzu-utils
Version: 0.9.3
Summary: Various utility functions and data structures used by the other pudzu packages
Home-page: https://github.com/Udzu/pudzu-packages/pudzu-utils/
License: MIT
Keywords: pudzu,utilities
Author: Uri Granta
Author-email: uri.granta+python@gmail.com
Requires-Python: >=3.7,<4.0
Classifier: License :: OSI Approved :: MIT License
Classifier: Operating System :: OS Independent
Classifier: Programming Language :: Python :: 3
Classifier: Programming Language :: Python :: 3.7
Classifier: Programming Language :: Python :: 3.8
Classifier: Programming Language :: Python :: 3.9
Classifier: Programming Language :: Python :: 3.10
Classifier: Programming Language :: Python :: 3.11
Classifier: Programming Language :: Python :: 3.12
Requires-Dist: toolz (>=0.11.1,<0.12.0)
